perfnetto-0.1.0.dist-info/RECORD
perfnetto-0.1.0.dist-info/METADATA
perfnetto-0.1.0.dist-info/WHEEL
perfnetto-0.1.0.dist-info/licenses/LICENSE
perfnetto/_perfnetto.cpython-313-x86_64-linux-gnu.so
perfnetto/__init__.py
perfnetto/py.typed
